Cath/__init__.py
Cath-1.3.dist-info/LICENSE
Cath-1.3.dist-info/METADATA
Cath-1.3.dist-info/WHEEL
Cath-1.3.dist-info/top_level.txt
Cath-1.3.dist-info/RECORD
