Metadata-Version: 2.1
Name: Cath
Version: 1.3
Summary: Python Turtle Graphics in 3D
Home-page: https://github.com/Heono
Author: Heono
Author-email: chooheonoh@gmail.com
License: MIT
Platform: UNKNOWN
Requires-Dist: pyzmq (==19.0.0)
